Workbook

Sheet INSTRUCTIONS
B1: BCST Wholesale Credit Risk — Stress Testing Input File
B2: Basel Credit Stress Testing (BCST) — Data Input Workbook v1.0
B4: Sheet | C4: Description | D4: Color Code
B5: 1. INSTRUCTIONS | C5: This sheet — file overview and color conventions | D5: —
B6: 2. SCENARIO_PARAMS | C6: Macroeconomic stress parameters for each scenario | D6: Blue = inputs
B7: 3. PORTFOLIO_EXPOSURE | C7: Sector-level EAD, ratings, base PD, LGD inputs | D7: Blue = inputs
B8: 4. PD_MIGRATION_MATRIX | C8: Base transition matrix (6×7 rating migration) | D8: Blue = inputs
B9: 5. HEATMAP_EL | C9: Sector × Rating EL inputs for heatmap visualisation | D9: Blue = inputs
B10: 6. BCST_RULES | C10: BCST regulatory rule thresholds and actual values | D10: Yellow = review
B11: 7. WATERFALL_PD | C11: PD shock attribution inputs per scenario | D11: Blue = inputs
B12: 8. DASHBOARD_LOOKUP | C12: Auto-computed lookup table — DO NOT EDIT | D12: Black = formulas
B16: COLOR CONVENTIONS
B17: ■ Blue text — Hardcoded input (user-editable)
B18: ■ Black text — Formula / auto-calculated cell
B19: ■ Yellow bg — Key assumption requiring review
B20: ■ Green text — Cross-sheet formula link

Sheet SCENARIO_PARAMS
B1: SCENARIO_PARAMS — Macroeconomic Stress Parameters
B2: Parameter | C2: Baseline | D2: Adverse | E2: Severely Adverse | F2: Custom
B3: Scenario ID | C3: BASE | D3: ADV | E3: SEV | F3: CUST
B4: Scenario Label | C4: Baseline | D4: Adverse | E4: Severely Adverse | F4: Custom
B5: Effective Date | C5: 2025-03-31 | D5: 2025-03-31 | E5: 2025-03-31 | F5: 2025-03-31
B6: GDP Growth Shock (%) | C6: -0.005 | D6: -0.028 | E6: -0.058 | F6: -0.04
B7: Unemployment Rate Chg (%) | C7: 0.003 | D7: 0.018 | E7: 0.042 | F7: 0.025
B8: CDS Spread Widening (bps) | C8: 40 | D8: 180 | E8: 420 | F8: 260
B9: NPA Movement (bps) | C9: 15 | D9: 42 | E9: 78 | F9: 58
B10: Interest Rate Shock (%) | C10: 0.005 | D10: 0.018 | E10: 0.035 | F10: 0.026
B11: Equity Market Decline (%) | C11: -0.05 | D11: -0.28 | E11: -0.52 | F11: -0.38
B12: FX Depreciation (INR/%) | C12: 0.02 | D12: 0.1 | E12: 0.22 | F12: 0.15
B13: PD Multiplier (x) | C13: 1 | D13: 2.1 | E13: 3.6 | F13: 2.7
B14: LGD Multiplier (x) | C14: 1 | D14: 1.18 | E14: 1.38 | F14: 1.25
B15: Collateral Haircut Uplift (%) | C15: 0 | D15: 0.08 | E15: 0.18 | F15: 0.12
B16: Sector Correlation Stress | C16: 0 | D16: 0.15 | E16: 0.3 | F16: 0.2
B17: Severity Level | C17: Mild | D17: Moderate | E17: Severe | F17: User

Sheet PORTFOLIO_EXPOSURE
B1: PORTFOLIO_EXPOSURE — Sector-Level Wholesale Credit Inputs
B2: Sector | C2: EAD (₹ Cr) | D2: Rating | E2: Base PD (%) | F2: LGD (%) | G2: RWA Weight (%) | H2: Collateral (₹ Cr) | I2: Sector Code | J2: BCST Sector Flag | K2: Notes
B3: Infrastructure | C3: 28400 | D3: BBB | E3: 0.029 | F3: 0.44 | G3: 1 | H3: 18200 | I3: INFRA | J3: Y
B4: Real Estate / NBFC | C4: 22100 | D4: BB | E4: 0.058 | F4: 0.52 | G4: 1.5 | H4: 9800 | I4: RE_NBFC | J4: Y
B5: Steel & Metals | C5: 18700 | D5: A | E5: 0.021 | F5: 0.38 | G5: 0.85 | H5: 12400 | I5: STEEL | J5: Y
B6: Power & Energy | C6: 17200 | D6: BBB | E6: 0.034 | F6: 0.46 | G6: 1 | H6: 11600 | I6: POWER | J6: Y
B7: Textiles | C7: 12400 | D7: B | E7: 0.082 | F7: 0.58 | G7: 2 | H7: 3800 | I7: TXTL | J7: Y
B8: Telecom | C8: 11800 | D8: BBB | E8: 0.031 | F8: 0.42 | G8: 0.9 | H8: 7400 | I8: TELCO | J8: Y
B9: Chemicals / Pharma | C9: 9600 | D9: AA | E9: 0.009 | F9: 0.32 | G9: 0.7 | H9: 8200 | I9: CHEM | J9: N
B10: Auto / Ancillaries | C10: 8200 | D10: A | E10: 0.018 | F10: 0.36 | G10: 0.8 | H10: 5600 | I10: AUTO | J10: N
B11: Agri & Food Processing | C11: 7100 | D11: BB | E11: 0.045 | F11: 0.48 | G11: 1.2 | H11: 2800 | I11: AGRI | J11: Y
B12: TOTAL | C12: =SUM(C3:C11) -> 135500

Sheet PD_MIGRATION_MATRIX
B1: PD_MIGRATION_MATRIX — Base Annual Transition Matrix (%)
B2: From \ To | C2: → AAA | D2: → AA | E2: → A | F2: → BBB | G2: → BB | H2: → B | I2: → Default | J2: Row Sum
B3: AAA | C3: 0.882 | D3: 0.071 | E3: 0.028 | F3: 0.012 | G3: 0.004 | H3: 0.002 | I3: 0.001 | J3: =SUM(C3:I3) -> 1
B4: AA | C4: 0.009 | D4: 0.846 | E4: 0.084 | F4: 0.038 | G4: 0.015 | H4: 0.005 | I4: 0.003 | J4: =SUM(C4:I4) -> 1
B5: A | C5: 0.002 | D5: 0.024 | E5: 0.801 | F5: 0.112 | G5: 0.042 | H5: 0.014 | I5: 0.005 | J5: =SUM(C5:I5) -> 1
B6: BBB | C6: 0.001 | D6: 0.004 | E6: 0.048 | F6: 0.742 | G6: 0.126 | H6: 0.058 | I6: 0.021 | J6: =SUM(C6:I6) -> 1
B7: BB | C7: 0 | D7: 0.001 | E7: 0.008 | F7: 0.072 | G7: 0.684 | H7: 0.162 | I7: 0.073 | J7: =SUM(C7:I7) -> 1
B8: B | C8: 0 | D8: 0.001 | E8: 0.002 | F8: 0.014 | G8: 0.098 | H8: 0.621 | I8: 0.264 | J8: =SUM(C8:I8) -> 1

Sheet HEATMAP_EL
B1: HEATMAP_EL — Stressed EL by Sector × Rating Bucket (₹ Cr)
B2: Sector \ Rating | C2: AAA | D2: AA | E2: A | F2: BBB | G2: BB | H2: B | I2: Row Total
B3: Infrastructure | C3: 2 | D3: 4 | E3: 8 | F3: 14 | G3: 32 | H3: 48 | I3: =SUM(C3:H3) -> 108
B4: Real Estate / NBFC | C4: 5 | D4: 10 | E4: 18 | F4: 32 | G4: 72 | H4: 112 | I4: =SUM(C4:H4) -> 249
B5: Steel & Metals | C5: 1 | D5: 3 | E5: 6 | F5: 11 | G5: 24 | H5: 38 | I5: =SUM(C5:H5) -> 83
B6: Power & Energy | C6: 3 | D6: 6 | E6: 12 | F6: 22 | G6: 48 | H6: 74 | I6: =SUM(C6:H6) -> 165
B7: Textiles | C7: 8 | D7: 15 | E7: 26 | F7: 44 | G7: 92 | H7: 148 | I7: =SUM(C7:H7) -> 333
B8: Auto / Ancillaries | C8: 1 | D8: 2 | E8: 4 | F8: 8 | G8: 18 | H8: 28 | I8: =SUM(C8:H8) -> 61
B9: Column Total | C9: =SUM(C3:C8) -> 20 | D9: =SUM(D3:D8) -> 40 | E9: =SUM(E3:E8) -> 74 | F9: =SUM(F3:F8) -> 131 | G9: =SUM(G3:G8) -> 286 | H9: =SUM(H3:H8) -> 448 | I9: =SUM(I3:I8) -> 999

Sheet BCST_RULES
B1: BCST_RULES — Regulatory Rule Thresholds & Compliance Tracking
B2: Rule Code | C2: Rule Name | D2: Description | E2: Threshold | F2: Actual Value | G2: Status | H2: BCST Reference
B3: BCST §3.1 | C3: Min Stress Coverage | D3: Scenarios must cover ≥3 severity levels | E3: ≥3 scenarios | F3: 5 / 5 covered | G3: PASS | H3: BCST 2024 §3.1.2
B4: BCST §4.3 | C4: Single CParty Limit | D4: No single exposure >15% of Tier-1 Capital | E4: ≤15% T1 Cap | F4: 14.2% | G4: WARN | H4: BCST 2024 §4.3.1
B5: BCST §4.5 | C5: Sector Conc. Cap | D5: NBFC/RE sector ≤20% total wholesale book | E5: ≤20% book | F5: 22.1% | G5: FAIL | H5: BCST 2024 §4.5.3
B6: BCST §5.2 | C6: PD Floor (Stressed) | D6: Stressed PD floor: Inv. Grade ≥0.5% | E6: ≥0.50% IG | F6: Compliant | G6: PASS | H6: BCST 2024 §5.2.1
B7: BCST §6.1 | C7: LGD Haircut Floor | D7: Collateral haircut ≥20% under adverse scenario | E7: ≥20% haircut | F7: Applied 28% | G7: PASS | H7: BCST 2024 §6.1.4
B8: BCST §7.2 | C8: Capital Adequacy Buffer | D8: Post-stress CET1 must remain ≥7.5% | E8: ≥7.5% CET1 | F8: 8.14% | G8: WARN | H8: BCST 2024 §7.2.2
B9: BCST §8.1 | C9: Data Completeness | D9: ≥95% coverage of wholesale book required | E9: ≥95% coverage | F9: 98.4% | G9: PASS | H9: BCST 2024 §8.1.1
B10: BCST §9.3 | C10: Reverse Stress Test | D10: Reverse stress test must be conducted annually | E10: Annual | F10: Completed | G10: PASS | H10: BCST 2024 §9.3.0

Sheet WATERFALL_PD
B1: WATERFALL_PD — PD Shock Attribution by Macro Driver
B2: PD Component | C2: Baseline | D2: Adverse | E2: Severely Adverse | F2: Custom | G2: Attribution Factor | H2: Notes
B3: Baseline PD | C3: 0.0124 | D3: 0.0124 | E3: 0.0124 | F3: 0.0124 | G3: — | H3: Starting base PD (portfolio avg)
B4: GDP Shock Add-on | C4: 0 | D4: 0.0112 | E4: 0.0248 | F4: 0.0164 | G4: GDPShock×(-0.38) | H4: GDP contraction driver
B5: CDS Widening Add-on | C5: 0 | D5: 0.0062 | E5: 0.0148 | F5: 0.0088 | G5: CDSbps×0.0032 | H5: Credit spread widening
B6: NPA Contagion | C6: 0 | D6: 0.0054 | E6: 0.01 | F6: 0.0074 | G6: NPAbps×0.0048 | H6: NPA propagation effect
B7: Rate Shock Add-on | C7: 0 | D7: 0.003 | E7: 0.0091 | F7: 0.0045 | G7: RateShock×0.16 | H7: Interest rate stress
B8: Stressed PD (Total) | C8: 0.0124 | D8: 0.0382 | E8: 0.0711 | F8: 0.0495 | G8: Σ all components | H8: BCST §5.2 floor applied

Sheet DASHBOARD_LOOKUP
B1: DASHBOARD_LOOKUP — DO NOT EDIT (Auto-Calculated)
B2: Metric | C2: Value (Adverse) | D2: Source Sheet
B3: ECL — Adverse (₹ Cr) | C3: =ROUND(SUMPRODUCT(PORTFOLIO_EXPOSURE!C3:C11,PORTFOLIO_EXPOSURE!E3:E11*SCENARIO_PARAMS!D12,PORTFOLIO_EXPOSURE!F3:F11*SCENARIO_PARAMS!D13),0) -> 509 | D3: Auto
B4: Portfolio Avg Stressed PD | C4: =AVERAGE(PORTFOLIO_EXPOSURE!E3:E11)*SCENARIO_PARAMS!D12 -> 0.0036333333 | D4: Auto
B5: Total EAD (₹ Cr) | C5: =PORTFOLIO_EXPOSURE!C12 -> 135500 | D5: PORTFOLIO_EXPOSURE
B6: BCST Rules Breached | C6: =COUNTIF(BCST_RULES!G3:G10,"FAIL")+COUNTIF(BCST_RULES!G3:G10,"WARN") -> 3 | D6: BCST_RULES
B7: Stressed PD (Baseline) | C7: =WATERFALL_PD!C8 -> 0.0124 | D7: WATERFALL_PD
B8: Stressed PD (Adverse) | C8: =WATERFALL_PD!D8 -> 0.0382 | D8: WATERFALL_PD
B9: Stressed PD (Severely Adv) | C9: =WATERFALL_PD!E8 -> 0.0711 | D9: WATERFALL_PD
B10: Total Heatmap EL (₹ Cr) | C10: =HEATMAP_EL!I9 -> 999 | D10: HEATMAP_EL
